pyvidardb
pyvidardb/pyvidardb
