Metadata-Version: 2.1
Name: PyVidarDB
Version: 0.1.0
Summary: Python Wrapper for VidarDB
Home-page: https://github.com/vidardb/PyVidarDB
Author: VidarDB Team
Author-email: info@vidardb.com
License: UNKNOWN
Platform: UNKNOWN
Classifier: Programming Language :: Python :: 3
Classifier: License :: OSI Approved :: Apache Software License
Classifier: Operating System :: OS Independent
Requires-Python: >=3.5
